MANIFEST.in
README.rst
setup.cfg
setup.py
tw2/__init__.py
tw2.jqplugins.cookies.egg-info/PKG-INFO
tw2.jqplugins.cookies.egg-info/SOURCES.txt
tw2.jqplugins.cookies.egg-info/dependency_links.txt
tw2.jqplugins.cookies.egg-info/entry_points.txt
tw2.jqplugins.cookies.egg-info/namespace_packages.txt
tw2.jqplugins.cookies.egg-info/not-zip-safe
tw2.jqplugins.cookies.egg-info/requires.txt
tw2.jqplugins.cookies.egg-info/top_level.txt
tw2/jqplugins/__init__.py
tw2/jqplugins/cookies/__init__.py
tw2/jqplugins/cookies/base.py
tw2/jqplugins/cookies/defaults.py
tw2/jqplugins/cookies/static/jquery/cookies/js/jquery.cookies.js