Metadata-Version: 1.0
Name: tw2.jqplugins.cookies
Version: 2.0.0
Summary: toscawidgets2 wrapper for jquery cookie utilities.
Home-page: http://github.com/toscawidgets/tw2.jqplugins.cookies
Author: Ralph Bean
Author-email: rbean@redhat.com
License: MIT
Keywords: toscawidgets.widgets
Platform: UNKNOWN
Classifier: Development Status :: 3 - Alpha
Classifier: Environment :: Web Environment
Classifier: Environment :: Web Environment :: ToscaWidgets
Classifier: Topic :: Software Development :: Libraries :: Python Modules
Classifier: Topic :: Software Development :: Widget Sets
Classifier: Intended Audience :: Developers
Classifier: Operating System :: OS Independent
Classifier: Programming Language :: Python
